autofeatselect/__init__.py
autofeatselect/auto_feat_select.py
autofeatselect/modeling.py
AutoFeatSelect-0.1.5.dist-info/LICENSE.txt
AutoFeatSelect-0.1.5.dist-info/METADATA
AutoFeatSelect-0.1.5.dist-info/WHEEL
AutoFeatSelect-0.1.5.dist-info/top_level.txt
AutoFeatSelect-0.1.5.dist-info/RECORD
