Metadata-Version: 2.1
Name: AutoFeatSelect
Version: 0.1.5
Summary: Automated Feature Selection & Feature Importance Calculation Framework
Home-page: https://github.com/dorukcanga/AutoFeatSelect
Author: Doruk Canga
Author-email: dorukcanga@gmail.com
License: MIT
Platform: UNKNOWN
Classifier: Programming Language :: Python :: 3
Classifier: License :: OSI Approved :: MIT License
Classifier: Operating System :: OS Independent
License-File: LICENSE.txt
Requires-Dist: category-encoders
Requires-Dist: xgboost
Requires-Dist: lightgbm
Requires-Dist: Boruta
